MANIFEST.in
README.md
README.rst
gpgmailencrypt.py
setup.py
documentation/__init__.py
documentation/gpgmailencrypt documentation.odt
documentation/gpgmailencrypt documentation.pdf
gmeutils/__init__.py
gmeutils/_dbg.py
gmeutils/adminconsole.py
gmeutils/archivemanagers.py
gmeutils/child.py
gmeutils/dkim.py
gmeutils/gpgclass.py
gmeutils/gpgmailserver.py
gmeutils/helpers.py
gmeutils/mylogger.py
gmeutils/mytimer.py
gmeutils/password.py
gmeutils/pdfclass.py
gmeutils/smimeclass.py
gmeutils/spamscanners.py
gmeutils/storagebackend.py
gmeutils/usage.py
gmeutils/version.py
gmeutils/viruscheck.py
gmeutils/virusscanners.py
gmeutils/thirdparty/__init__.py
gmeutils/thirdparty/dkimpy.license
gmeutils/thirdparty/email2pdf.license
gmeutils/thirdparty/email2pdf.py
gmeutils/thirdparty/dkim/__init__.py
gmeutils/thirdparty/dkim/__main__.py
gmeutils/thirdparty/dkim/asn1.py
gmeutils/thirdparty/dkim/canonicalization.py
gmeutils/thirdparty/dkim/crypto.py
gmeutils/thirdparty/dkim/dnsplug.py
gmeutils/thirdparty/dkim/util.py
gpgmailencrypt.egg-info/PKG-INFO
gpgmailencrypt.egg-info/SOURCES.txt
gpgmailencrypt.egg-info/dependency_links.txt
gpgmailencrypt.egg-info/requires.txt
gpgmailencrypt.egg-info/top_level.txt
mailtemplates/__init__.py
mailtemplates/DE/01-pdfpassword.html
mailtemplates/DE/02-pdfmail.html
mailtemplates/DE/03-virusinformation.html
mailtemplates/DE/04-bouncemail.html
mailtemplates/EN/00-template.html
mailtemplates/EN/01-pdfpassword.html
mailtemplates/EN/02-pdfmail.html
mailtemplates/EN/03-virusinformation.html
mailtemplates/EN/04-bouncemail.html
mailtemplates/FR/01-pdfpassword.html
mailtemplates/FR/02-pdfmail.html
misc/__init__.py
misc/gpgmailencrypt.init
misc/gpgmailencrypt.service
scripts/encryptmaildir.py
scripts/gme.py
scripts/gme_admin.py
tests/.coverage
tests/__init__.py
tests/archives
tests/attachment.eml
tests/content
tests/dkim
tests/gmetest.conf
tests/gmetest.sqlite.conf
tests/gmetest.sqlite.orig
tests/gmetest.sqlitecreatetables.conf
tests/gmetest2.conf
tests/gmeunittests.py
tests/gpg
tests/gpgmailencrypt.pw.orig
tests/pdfpasswords.pw
tests/smime
tests/source.txt
tests/testgmeunittests.py
tests/testscript.sh
tests/virus
tests/ziponecontainerorig.eml
