Metadata-Version: 1.1
Name: gpgmailencrypt
Version: 3.4.6
Summary: an e-mail encryption, virus- and spam- checking module, gateway and daemon
Home-page: https://github.com/gpgmailencrypt/gpgmailencrypt
Author: Horst Knorr
Author-email: gpgmailencrypt@gmx.de
License: GPL v3
Keywords: Email encryption daemon gateway  gpg pgp smime pdf spam spamassassin bogofilter virus clamav drwatson avast f-prot fprot sophos bitdefender mysql sqlite postgres
Platform: UNKNOWN
Classifier: Development Status :: 5 - Production/Stable
Classifier: Intended Audience :: Developers
Classifier: Intended Audience :: System Administrators
Classifier: Intended Audience :: Information Technology
Classifier: Environment :: No Input/Output (Daemon)
Classifier: Environment :: Console
Classifier: Topic :: Software Development :: Build Tools
Classifier: License :: OSI Approved :: GNU General Public License v3 (GPLv3)
Classifier: Programming Language :: Python :: 3
Classifier: Programming Language :: Python :: 3.4
Classifier: Programming Language :: Python :: 3.5
Classifier: Programming Language :: Python :: 3.6
Classifier: Topic :: Communications :: Email :: Mail Transport Agents
Classifier: Topic :: Communications :: Email
Classifier: Topic :: Database
Classifier: Topic :: Security :: Cryptography
Classifier: Topic :: Software Development :: Libraries :: Python Modules
Classifier: Operating System :: OS Independent
